discordpy_logging_handler/__init__.py
discordpy_logging_handler/_datetime.py
discordpy_logging_handler/_embed.py
discordpy_logging_handler/handler.py
poetry.lock
tox.ini
discordpy_logging_handler-0.1.0.dist-info/WHEEL
discordpy_logging_handler-0.1.0.dist-info/METADATA
discordpy_logging_handler-0.1.0.dist-info/RECORD
